pytest_marker_bugzilla.py
pytest_marker_bugzilla-0.9.5.dist-info/licenses/AUTHORS
pytest_marker_bugzilla-0.9.5.dist-info/METADATA
pytest_marker_bugzilla-0.9.5.dist-info/WHEEL
pytest_marker_bugzilla-0.9.5.dist-info/entry_points.txt
pytest_marker_bugzilla-0.9.5.dist-info/pbr.json
pytest_marker_bugzilla-0.9.5.dist-info/top_level.txt
pytest_marker_bugzilla-0.9.5.dist-info/zip-safe
pytest_marker_bugzilla-0.9.5.dist-info/RECORD
