Metadata-Version: 2.4
Name: pytest-marker-bugzilla
Version: 0.9.5
Summary: py.test bugzilla integration plugin, using markers
Home-page: http://github.com/els-pnw/pytest_marker_bugzilla
Author: Eric Sammons, Lukas Bednar
Author-email: elsammons@gmail.com, lukyn17@gmail.com
License: GPL
Keywords: pytest,bugzilla,plugin
Classifier: Development Status :: 5 - Production/Stable
Classifier: Intended Audience :: Developers
Classifier: License :: OSI Approved :: GNU General Public License (GPL)
Classifier: Environment :: Plugins
Classifier: Framework :: Pytest
Classifier: Operating System :: POSIX
Classifier: Operating System :: Microsoft :: Windows
Classifier: Operating System :: MacOS :: MacOS X
Classifier: Programming Language :: Python
Classifier: Programming Language :: Python :: 2.7
Classifier: Programming Language :: Python :: 3.6
Classifier: Topic :: Software Development :: Testing
Classifier: Topic :: Software Development :: Quality Assurance
Classifier: Topic :: Utilities
License-File: AUTHORS
Requires-Dist: python-bugzilla>=0.6.2
Requires-Dist: pytest>=2.2.4
Requires-Dist: six
Dynamic: author
Dynamic: author-email
Dynamic: home-page
Dynamic: keywords
Dynamic: license
Dynamic: license-file
Dynamic: requires-dist
Dynamic: summary
